Reporter/__init__.py
Reporter/data_frames/__init__.py
Reporter/data_frames/abs_source_data_frame.py
Reporter/data_frames/cell.py
Reporter/data_frames/excel_data_frame.py
Reporter/data_sources/__init__.py
Reporter/data_sources/abs_source.py
Reporter/data_sources/data_sources.py
Reporter/data_sources/df_processor.py
Reporter/data_sources/file_source.py
Reporter/data_sources/source_manager.py
Reporter/data_sources/table_source.py
Reporter/data_sources/excel/__init__.py
Reporter/data_sources/excel/excel_source.py
Reporter/data_sources/sharepoint/__init__.py
Reporter/data_sources/sharepoint/sharepoint.py
Reporter/data_sources/sharepoint/sharepoint_source.py
Reporter/data_sources/sql/__init__.py
Reporter/data_sources/sql/logical.py
Reporter/data_sources/sql/odbc_conn.py
Reporter/data_sources/sql/sql_conn.py
Reporter/data_sources/sql/sql_join.py
Reporter/data_sources/sql/sql_query.py
Reporter/data_sources/sql/sql_source.py
Reporter/data_sources/web_scrape/__init__.py
Reporter/data_sources/web_scrape/web_source.py
Reporter/events/__init__.py
Reporter/events/event.py
Reporter/events/export_events.py
Reporter/events/out_event.py
Reporter/events/progress_event.py
Reporter/exceptions/__init__.py
Reporter/exceptions/abs_except.py
Reporter/exceptions/data_except.py
Reporter/exceptions/file_except.py
Reporter/exceptions/sharepoint_except.py
Reporter/file_manager/__init__.py
Reporter/file_manager/file.py
Reporter/file_manager/file_group_manager.py
Reporter/file_manager/file_manager.py
Reporter/tools/__init__.py
Reporter/tools/colours.py
Reporter/tools/dataframe_tools.py
Reporter/tools/date_tools.py
Reporter/tools/driver_tools.py
Reporter/tools/excel.py
Reporter/tools/url_tools.py
Reporter/view/__init__.py
Reporter/view/export.py
Reporter/view/progress.py
Reporter/view/report.py
Reporter/view/subject.py
Reporter/view/observers/__init__.py
Reporter/view/observers/excel_export_observer.py
Reporter/view/observers/excel_observer.py
Reporter/view/observers/observer.py
PyReporter-1.0.10.dist-info/LICENSE
PyReporter-1.0.10.dist-info/METADATA
PyReporter-1.0.10.dist-info/WHEEL
PyReporter-1.0.10.dist-info/top_level.txt
PyReporter-1.0.10.dist-info/RECORD
